CAD_Recognition_1/__init__.py
CAD_Recognition_1/data_load.py
CAD_Recognition_1/features.py
CAD_Recognition_1/programs.py
my_CAD-1.0.0.dist-info/METADATA
my_CAD-1.0.0.dist-info/WHEEL
my_CAD-1.0.0.dist-info/top_level.txt
my_CAD-1.0.0.dist-info/RECORD
