Metadata-Version: 2.1
Name: my-CAD
Version: 1.0.0
Summary: CAD recognition programs.
Home-page: https://github.com/kenblikylee/imgkernel
Author: francis
Author-email: francisrk@163.com
License: UNKNOWN
Platform: UNKNOWN
Classifier: Programming Language :: Python :: 3
Classifier: Operating System :: OS Independent
Requires-Python: ==3.5
